<gresources>
  <gresource prefix="/org/rafaello7/wilqpaint">
    <file preprocess="xml-stripblanks">wilqpaint.ui</file>
    <file preprocess="xml-stripblanks">sizedialog.ui</file>
    <file preprocess="xml-stripblanks">griddialog.ui</file>
    <file preprocess="xml-stripblanks">quitdialog.ui</file>
    <file preprocess="xml-stripblanks">menubar.ui</file>
    <file>img/wilqpaint.png</file>
    <file>img/select.png</file>
    <file>img/imagesize.png</file>
    <file>img/text.png</file>
    <file>img/free.png</file>
    <file>img/line.png</file>
    <file>img/arrow.png</file>
    <file>img/triangle.png</file>
    <file>img/rectangle.png</file>
    <file>img/oval.png</file>
    <file>img/transparency.png</file>
    <file>img/pin_top.png</file>
    <file>img/pin_right.png</file>
    <file>img/pin_bottom.png</file>
    <file>img/pin_left.png</file>
    <file>img/pin_center.png</file>
  </gresource>
</gresources>
